main.py
smartloop/__init__.py
smartloop/app.py
smartloop/constants.py
smartloop/cmd/__init__.py
smartloop/cmd/projects.py
smartloop/services/__init__.py
smartloop/services/projects.py
smartloop/utils/__init__.py
smartloop/utils/user_profile.py
smartloop/utils/templates/callback.html
smartloop-1.3.2.dist-info/licenses/LICENSE.txt
smartloop-1.3.2.dist-info/METADATA
smartloop-1.3.2.dist-info/WHEEL
smartloop-1.3.2.dist-info/entry_points.txt
smartloop-1.3.2.dist-info/top_level.txt
smartloop-1.3.2.dist-info/RECORD
