Metadata-Version: 2.4
Name: smartloop
Version: 1.3.2
Summary: Smartloop Command Line interface to process documents using LLM
Home-page: https://github.com/LexicHQ/smartloop
Author: Smartloop Inc.
Author-email: hello@smartloop.ai
License: LICENSE.txt
Keywords: LLM,framework,fine-tuning,platform,document-processing,ai
Classifier: Development Status :: 4 - Beta
Classifier: Intended Audience :: Developers
Classifier: Topic :: Software Development :: Libraries
Classifier: License :: OSI Approved :: MIT License
Classifier: Programming Language :: Python :: 3.10
Classifier: Programming Language :: Python :: 3.11
License-File: LICENSE.txt
Requires-Dist: PyYAML==6.0.1
Requires-Dist: requests==2.32.3
Requires-Dist: typer==0.12.3
Requires-Dist: inquirer==3.3.0
Requires-Dist: tabulate==0.9.0
Requires-Dist: pyfiglet==1.0.4
Dynamic: author
Dynamic: author-email
Dynamic: classifier
Dynamic: description
Dynamic: description-content-type
Dynamic: home-page
Dynamic: keywords
Dynamic: license
Dynamic: license-file
Dynamic: requires-dist
Dynamic: summary
